jast/__init__.py
jast/babel.py
jast/custom.py
jast/util.py
jast-1.0.0b1.dist-info/METADATA
jast-1.0.0b1.dist-info/WHEEL
jast-1.0.0b1.dist-info/top_level.txt
jast-1.0.0b1.dist-info/RECORD
