Metadata-Version: 2.1
Name: jast
Version: 1.0.0b1
Summary: Construct javascript AST structures using python objects.
Home-page: https://github.com/grnet/jast
Author: Kostas Papadimitriou
Author-email: kpap@grnet.gr
License: UNKNOWN
Platform: UNKNOWN
Classifier: Development Status :: 3 - Alpha
Classifier: Intended Audience :: Developers
Classifier: License :: OSI Approved :: GNU Affero General Public License v3 or later (AGPLv3+)
Classifier: Programming Language :: Python
Classifier: Programming Language :: Python :: 2
Classifier: Programming Language :: Python :: 2.7
Requires-Dist: setuptools
Requires-Dist: attrs (==18.1.0)
Requires-Dist: cattrs (==0.8.0)
Requires-Dist: inflection (==0.3.1)
Provides-Extra: rest
Requires-Dist: Sphinx ; extra == 'rest'
